cloudproof_ecies-0.1.4.dist-info/METADATA
cloudproof_ecies-0.1.4.dist-info/WHEEL
cloudproof_ecies-0.1.4.dist-info/license_files/LICENSE.md
cloudproof_ecies/__init__.pyi
cloudproof_ecies/__init__.py
cloudproof_ecies/py.typed
cloudproof_ecies/cloudproof_ecies.abi3.so
cloudproof_ecies-0.1.4.dist-info/RECORD
